README.md
setup.py
py_sphviewer.egg-info/PKG-INFO
py_sphviewer.egg-info/SOURCES.txt
py_sphviewer.egg-info/dependency_links.txt
py_sphviewer.egg-info/requires.txt
py_sphviewer.egg-info/top_level.txt
sphviewer/Camera.py
sphviewer/Particles.py
sphviewer/README.txt
sphviewer/Render.py
sphviewer/Scene.py
sphviewer/__init__.py
sphviewer/c_code.c
sphviewer/extra_code.c
sphviewer/version.py
sphviewer/extensions/__init__.py
sphviewer/extensions/rendermodule.c
sphviewer/extensions/scenemodule.c
sphviewer/tools/Blend.py
sphviewer/tools/QuickView.py
sphviewer/tools/__init__.py
sphviewer/tools/camera_tools.py
sphviewer/tools/cmaps.py
sphviewer/tools/hsv_tools.py
sphviewer/tools/makehsvmodule.c