Metadata-Version: 1.1
Name: py-sphviewer
Version: 1.2.0
Summary: Py-SPHViewer is a framework for rendering particles using the smoothed particle hydrodynamics scheme.
Home-page: https://github.com/alejandrobll/py-sphviewer
Author: Alejandro Benitez Llambay
Author-email: alejandrobll@oac.uncor.edu
License: GNU GPL v3
Keywords: smoothed particle hydrodynamics render particles nbody galaxy formation dark matter sph cosmology movies
Platform: UNKNOWN
Classifier: Programming Language :: Python :: 2.7
Classifier: Programming Language :: Python :: 3.6
Classifier: Topic :: Multimedia :: Graphics
Classifier: Topic :: Multimedia :: Graphics :: 3D Rendering
Classifier: Topic :: Multimedia :: Graphics :: Viewers
Classifier: Topic :: Scientific/Engineering :: Visualization
Classifier: Topic :: Utilities
Requires: pykdtree
